graphs_jjarek/__init__.py
graphs_jjarek/heapq.py
graphs_jjarek/sp.py
graphs_jjarek-0.1.0.dist-info/METADATA
graphs_jjarek-0.1.0.dist-info/WHEEL
graphs_jjarek-0.1.0.dist-info/top_level.txt
graphs_jjarek-0.1.0.dist-info/RECORD
