Metadata-Version: 2.1
Name: graphs_jjarek
Version: 0.1.0
Summary: A package implementing Dijkstra's shortest path algorithm
Requires-Python: >=3.7
